LICENSE
MANIFEST.in
README.rst
buildout.cfg
requirements.txt
setup.py
version.txt
bob/__init__.py
bob.db.stare.egg-info/PKG-INFO
bob.db.stare.egg-info/SOURCES.txt
bob.db.stare.egg-info/dependency_links.txt
bob.db.stare.egg-info/entry_points.txt
bob.db.stare.egg-info/not-zip-safe
bob.db.stare.egg-info/requires.txt
bob.db.stare.egg-info/top_level.txt
bob/db/__init__.py
bob/db/stare/__init__.py
bob/db/stare/checkfiles.py
bob/db/stare/create.py
bob/db/stare/driver.py
bob/db/stare/models.py
bob/db/stare/query.py
bob/db/stare/stare_db_default.json
bob/db/stare/stare_test.csv
bob/db/stare/stare_train.csv
bob/db/stare/test.py
doc/guide.rst
doc/index.rst
doc/links.rst
doc/py_api.rst
doc/img/bob-128x128.png
doc/img/bob-favicon.ico
doc/img/bob-logo.png